CHANGELOG.md
LICENSE
pylav/__init__.py
pylav/__version__.py
pylav/_internals/__init__.py
pylav/_internals/functions.py
pylav/_internals/locales/bg-BG.po
pylav/_internals/locales/cs-CZ.po
pylav/_internals/locales/da-DK.po
pylav/_internals/locales/de-DE.po
pylav/_internals/locales/el-GR.po
pylav/_internals/locales/es-ES.po
pylav/_internals/locales/fi-FI.po
pylav/_internals/locales/fr-FR.po
pylav/_internals/locales/hi-IN.po
pylav/_internals/locales/hr-HR.po
pylav/_internals/locales/hu-HU.po
pylav/_internals/locales/it-IT.po
pylav/_internals/locales/ja-JP.po
pylav/_internals/locales/ko-KR.po
pylav/_internals/locales/lt-LT.po
pylav/_internals/locales/nb-NO.po
pylav/_internals/locales/nl-NL.po
pylav/_internals/locales/pl-PL.po
pylav/_internals/locales/pt-BR.po
pylav/_internals/locales/ro-RO.po
pylav/_internals/locales/ru-RU.po
pylav/_internals/locales/sv-SE.po
pylav/_internals/locales/th-TH.po
pylav/_internals/locales/tr-TR.po
pylav/_internals/locales/uk-UA.po
pylav/_internals/locales/vi-VN.po
pylav/_internals/locales/zh-CN.po
pylav/_internals/locales/zh-TW.po
pylav/_internals/pylav_yaml_builder.py
pylav/constants/__init__.py
pylav/constants/builtin_nodes.py
pylav/constants/city_dump.py
pylav/constants/config/__init__.py
pylav/constants/config/env_var.py
pylav/constants/config/file.py
pylav/constants/config/locales/bg-BG.po
pylav/constants/config/locales/cs-CZ.po
pylav/constants/config/locales/da-DK.po
pylav/constants/config/locales/de-DE.po
pylav/constants/config/locales/el-GR.po
pylav/constants/config/locales/es-ES.po
pylav/constants/config/locales/fi-FI.po
pylav/constants/config/locales/fr-FR.po
pylav/constants/config/locales/hi-IN.po
pylav/constants/config/locales/hr-HR.po
pylav/constants/config/locales/hu-HU.po
pylav/constants/config/locales/it-IT.po
pylav/constants/config/locales/ja-JP.po
pylav/constants/config/locales/ko-KR.po
pylav/constants/config/locales/lt-LT.po
pylav/constants/config/locales/nb-NO.po
pylav/constants/config/locales/nl-NL.po
py_lav-1.1.19.dist-info/WHEEL
py_lav-1.1.19.dist-info/LICENSE
py_lav-1.1.19.dist-info/METADATA
py_lav-1.1.19.dist-info/RECORD
